Workbook
Name B: Accounts!$B$190
Name B: Taxes!$B$181

Sheet CHART
B2: Allowance | F2: Stipend | I2: Maya
F7: GCash
I10: CIMB
F12: Savings

Sheet Allowance
B3: Balance | C3: {=SUMPRODUCT(Allowance!$D11:$F260*(((Allowance!$G11:$I260="Load")*(Allowance!$J11:$L260="Piggy"))+((Allowance!$G11:$I260="Piggy")*(Allowance!$J11:$L260="Load")))) - SUMPRODUCT(Allowance!$D11:$F260*((Allowance!$G11:$I260="Piggy")*(Allowance!$J11:$L260<>"Load"))) + S12} -> 0 | F3: Balance | H3: =SUMIFS(Allowance!$D11:$F260, Allowance!$G11:$I260, "Emergency", Allowance!$J11:$L260, "Load")-SUMIFS(Allowance!$D11:$F260, Allowance!$G11:$I260, "Emergency", Allowance!$J11:$L260, "<>Load") + S13 -> 0 | J3: Amount | L3: {=SUMPRODUCT(Allowance!$D11:$F260*((Allowance!$G11:$I260="Data")*(Allowance!$J11:$L260="Load"))) - SUMPRODUCT(Allowance!$D11:$F260*((Allowance!$G11:$I260="Data")*(Allowance!$J11:$L260<>"Load"))) + S14} -> 0 | N3: Amount | O3: {=SUMPRODUCT(Allowance!$D11:$F260*((Allowance!$G11:$I260="pookie")*(Allowance!$J11:$L260=""))) - SUMPRODUCT(Allowance!$D11:$F260*((Allowance!$G11:$I260="pookie")*(Allowance!$J11:$L260<>""))) + S20} -> 0
B6: Balance | D6: {=SUMPRODUCT(Allowance!$D11:$F260*((Allowance!$G11:$I260="Beep")*(Allowance!$J11:$L260="Load"))) - SUMPRODUCT(Allowance!$D11:$F260*((Allowance!$G11:$I260="Beep")*((Allowance!$J11:$L260<>"Load")*(Allowance!$J11:$L260<>"Hold")))) + S16} -> 0 | F6: Balance | H6: {=(SUMPRODUCT(Allowance!$D11:$F260*((Allowance!$G11:$I260="Canva")*(Allowance!$J11:$L260="Hold"))) - SUMPRODUCT(Allowance!$D11:$F260*((Allowance!$G11:$I260="Canva")*(Allowance!$J11:$L260="Clear"))) + S17) - (PRODUCT(COUNTIFS(Allowance!$G11:$I260, "Canva", Allowance!$J11:$L260, "Clear"), 2940))} -> 0 | J6: Tax-Debt | K6: {=SUMPRODUCT(Allowance!$N11:$N260*(((Allowance!$G11:$I260="Tax")+(Allowance!$G11:$I260="Debt"))*(Allowance!$N11:$N260<>"")))} -> 0 | L6: {=K6 - SUMPRODUCT(Allowance!$D11:$F260*(((Allowance!$G11:$I260="Tax")+(Allowance!$G11:$I260="Debt"))*(Allowance!$N11:$N260<>""))) + S18} -> 0
B7: Hold | C7: {=SUMPRODUCT(Allowance!$D11:$F260*((Allowance!$G11:$I260="Beep")*(Allowance!$J11:$L260="Hold"))) + S15} -> 0 | F7: Left | G7: =G6-H6 -> 0 | J7: IponCard | K7: {=SUMPRODUCT(Allowance!$N11:$N260*((Allowance!$G11:$I260="IponCard")*(Allowance!$N11:$N260<>"")))} -> 0 | L7: {=K7 - SUMPRODUCT(Allowance!$D11:$F260*((Allowance!$G11:$I260="IponCard")*(Allowance!$N11:$N260<>""))) + S19} -> 0
D9: {=SUMPRODUCT(Allowance!$D11:$F260*(((Allowance!$G11:$I260="Load")*(Allowance!$J11:$L260<>"Piggy"))+((Allowance!$G11:$I260="Piggy")*(Allowance!$J11:$L260<>"Load"))+((Allowance!$G11:$I260="Tax")*(Allowance!$J11:$L260<>"Return"))+(((Allowance!$G11:$I260="Gala")+(Allowance!$G11:$I260="Gift")+(Allowance!$G11:$I260="Want"))*((Allowance!$J11:$L260="Load1")+(Allowance!$J11:$L260="Load2")+(Allowance!$J11:$L260="Load3"))))) + S11} -> 0 | G9: {=SUMPRODUCT(Allowance!$D11:$F260*((((Allowance!$G11:$I260="Piggy")+(Allowance!$G11:$I260="Data")+(Allowance!$G11:$I260="Emergency")+(Allowance!$G11:$I260="Beep"))*(Allowance!$J11:$L260="Load"))+((Allowance!$G11:$I260="IponCard")+(Allowance!$G11:$I260="Canva")+(Allowance!$G11:$I260="IponBox")+(Allowance!$G11:$I260="Item")+(Allowance!$G11:$I260="Food")+(Allowance!$G11:$I260="Grocery")+(Allowance!$G11:$I260="Transpo")+(Allowance!$G11:$I260="Savings")+(Allowance!$G11:$I260=""))+(((Allowance!$G11:$I260="Gala")+(Allowance!$G11:$I260="Gift")+(Allowance!$G11:$I260="Want"))*((Allowance!$J11:$L260="Slot1")+(Allowance!$J11:$L260="Slot2")+(Allowance!$J11:$L260="Slot3")))+((Allowance!$G11:$I260="Debt")*(Allowance!$J11:$L260<>"Paid"))+((Allowance!$G11:$I260="Beep")*(Allowance!$J11:$L260="Hold")) +((Allowance!$G11:$I260="pookie")*(Allowance!$J11:$L260="")))) + SUMPRODUCT(Stipend!$D4:$F253*((Stipend!$G4:$I253="Load")*(Stipend!$J4:$L253=""))) + SUMPRODUCT(GCash!$D4:$F253*((GCash!$G4:$I253="Load")*(GCash!$J4:$L253=""))) + SUMPRODUCT(Maya!$D5:$F254*(((Maya!$G5:$G254="Wallet")+(Maya!$G5:$G254="Savings"))*(Maya!$H5:$H254="Load")*(Maya!$I5:$K254="")+((Maya!$H5:$H254="Hold")*(Maya!$I5:$K254="Return")))) + SUMPRODUCT(CIMB!$D5:$F254*(((CIMB!$G5:$G254="UpSave")+(CIMB!$G5:$G254="GSave"))*(CIMB!$H5:$H254="Load")*(CIMB!$I5:$K254=""))) + SUMPRODUCT(Savings!$D6:$F255*(((Savings!$G4:$I253="Savings")+(Savings!$G4:$I253="Personal")+(Savings!$G4:$I253="pookie"))*(Savings!$J6:$L255="Save")))} -> 0 | J9: =D9-G9 -> 0
B10: DATE | D10: AMOUNT | G10: PURCHASE | J10: SPECIFIC | R10: BUDGET 1.5

Sheet Accounts
B2: CASH
B4: Stipend | F4: IponBox | J4: IponCard
B5: Balance | D5: =Stipend!J2 -> 0 | F5: Balance | G5: =IponBox!D3 -> 0 | H5: =IponBox!D3-IponBox!E3 -> 0 | J5: Balance | K5: {=_xlfn.LET(_xlpm.Bal, SUMPRODUCT(Allowance!$D11:$F260*(Allowance!$G11:$I260="IponCard")) + Allowance!S21, _xlpm.Bal - (PRODUCT(COUNTIFS(Allowance!$G11:$I260, "IponCard", Allowance!$J11:$L260, "Clear"), _xlpm.Bal)))} -> 0
B9: E-CASH
B11: CIMB | F11: Maya | J11: Savings
B12: Total Balance | D12: =SUM(D13:D14) -> 0 | F12: Total Balance | H12: =SUM(H13:H14) -> 0 | L12: =Savings!J4 -> 0
B13: UpSave | D13: =CIMB!I2 -> 0 | F13: Wallet | H13: =Maya!I2 -> 0 | L13: =Savings!J3 -> 0
B14: GSave | D14: =CIMB!I3 -> 0 | F14: Savings | G14: 0 | H14: =Maya!I3 -> 0 | L14: =Savings!J2 -> 0

Sheet IponBox
B2: Ipon Box Challenge
B3: Goal

Sheet Savings
J2: {=SUMPRODUCT(Savings!$D6:$F255*((Savings!$G6:$I255="Savings")*((Savings!$J6:$L255="Load")+(Savings!$J6:$L255="Interest")+(Savings!$J6:$L255="Save"))))} -> 0 | N2: January | P2: February | R2: March | T2: April | V2: May | X2: June | Z2: July | AB2: August | AD2: September | AF2: October | AH2: November | AJ2: December
J3: {=SUMPRODUCT(Savings!$D6:$F255*((Savings!$G6:$I255="pookie")*(Savings!$J6:$L255="Interest"))) + PRODUCT(50, SUM(O3:O4,Q3:Q4,S3:S4,U3:U4,W3:W4,Y3:Y4,AC3:AC4,AE3:AE4,AG3:AG4,AI3:AI4,AK3:AK4))} -> 0 | N3: 31 | O3: 0 | P3: 28 | Q3: 0 | R3: 31 | S3: 0 | T3: 30 | U3: 0 | V3: 31 | W3: 0 | X3: 30 | Y3: 0 | Z3: 31 | AA3: 0 | AB3: 31 | AC3: 0 | AD3: 30 | AE3: 0 | AF3: 31 | AG3: 0 | AH3: 30 | AI3: 0 | AJ3: 31 | AK3: 0
J4: {=SUMPRODUCT(Savings!$D6:$F255*((Savings!$G6:$I255="Personal")*((Savings!$J6:$L255="Load")+(Savings!$J6:$L255="Interest")+(Savings!$J6:$L255="Save"))))} -> 0 | O4: 0 | Q4: 0 | S4: 0 | U4: 0 | W4: 0 | Y4: 0 | AA4: 0 | AC4: 0 | AE4: 0 | AG4: 0 | AI4: 0 | AK4: 0
B5: DATE | D5: AMOUNT | G5: CATEGORY | J5: SPECIFIC

Sheet Taxes
B2: Gala | F2: Gifts | J2: Wants / Debt
B3: Transpo | D3: {=_xlfn.LET(_xlpm.Bal, SUMPRODUCT(Allowance!$D11:$F260*((Allowance!$G11:$I260="Gala")*(Allowance!$J11:$L260="Slot1"))) - SUMPRODUCT(Allowance!$D11:$F260*((Allowance!$G11:$I260="Gala")*(Allowance!$J11:$L260="Load1"))) + Allowance!S22, _xlpm.Bal - (PRODUCT(COUNTIFS(Allowance!$G11:$I260, "Gala", Allowance!$J11:$L260, "Clear1"), _xlpm.Bal)))} -> 0 | H3: {=_xlfn.LET(_xlpm.Bal, SUMPRODUCT(Allowance!$D11:$F260*((Allowance!$G11:$I260="Gift")*(Allowance!$J11:$L260="Slot1"))) - SUMPRODUCT(Allowance!$D11:$F260*((Allowance!$G11:$I260="Gift")*(Allowance!$J11:$L260="Load1"))) + Allowance!S25, _xlpm.Bal - (PRODUCT(COUNTIFS(Allowance!$G11:$I260, "Gift", Allowance!$J11:$L260, "Clear1"), _xlpm.Bal)))} -> 0 | L3: {=_xlfn.LET(_xlpm.Bal, SUMPRODUCT(Allowance!$D11:$F260*((Allowance!$G11:$I260="Want")*(Allowance!$J11:$L260="Slot1"))) - SUMPRODUCT(Allowance!$D11:$F260*((Allowance!$G11:$I260="Want")*(Allowance!$J11:$L260="Load1"))) + Allowance!S28, _xlpm.Bal - (PRODUCT(COUNTIFS(Allowance!$G11:$I260, "Want", Allowance!$J11:$L260, "Clear1"), _xlpm.Bal)))} -> 0
B4: Food | D4: {=_xlfn.LET(_xlpm.Bal, SUMPRODUCT(Allowance!$D11:$F260*((Allowance!$G11:$I260="Gala")*(Allowance!$J11:$L260="Slot2"))) - SUMPRODUCT(Allowance!$D11:$F260*((Allowance!$G11:$I260="Gala")*(Allowance!$J11:$L260="Load2"))) + Allowance!S23, _xlpm.Bal - (PRODUCT(COUNTIFS(Allowance!$G11:$I260, "Gala", Allowance!$J11:$L260, "Clear2"), _xlpm.Bal)))} -> 0 | H4: {=_xlfn.LET(_xlpm.Bal, SUMPRODUCT(Allowance!$D11:$F260*((Allowance!$G11:$I260="Gift")*(Allowance!$J11:$L260="Slot2"))) - SUMPRODUCT(Allowance!$D11:$F260*((Allowance!$G11:$I260="Gift")*(Allowance!$J11:$L260="Load2"))) + Allowance!S26, _xlpm.Bal - (PRODUCT(COUNTIFS(Allowance!$G11:$I260, "Gift", Allowance!$J11:$L260, "Clear2"), _xlpm.Bal)))} -> 0 | L4: {=_xlfn.LET(_xlpm.Bal, SUMPRODUCT(Allowance!$D11:$F260*((Allowance!$G11:$I260="Want")*(Allowance!$J11:$L260="Slot2"))) - SUMPRODUCT(Allowance!$D11:$F260*((Allowance!$G11:$I260="Want")*(Allowance!$J11:$L260="Load2"))) + Allowance!S29, _xlpm.Bal - (PRODUCT(COUNTIFS(Allowance!$G11:$I260, "Want", Allowance!$J11:$L260, "Clear2"), _xlpm.Bal)))} -> 0
B5: Activities | D5: {=_xlfn.LET(_xlpm.Bal, SUMPRODUCT(Allowance!$D11:$F260*((Allowance!$G11:$I260="Gala")*(Allowance!$J11:$L260="Slot3"))) - SUMPRODUCT(Allowance!$D11:$F260*((Allowance!$G11:$I260="Gala")*(Allowance!$J11:$L260="Load3"))) + Allowance!S24, _xlpm.Bal - (PRODUCT(COUNTIFS(Allowance!$G11:$I260, "Gala", Allowance!$J11:$L260, "Clear3"), _xlpm.Bal)))} -> 0 | H5: {=_xlfn.LET(_xlpm.Bal, SUMPRODUCT(Allowance!$D11:$F260*((Allowance!$G11:$I260="Gift")*(Allowance!$J11:$L260="Slot3"))) - SUMPRODUCT(Allowance!$D11:$F260*((Allowance!$G11:$I260="Gift")*(Allowance!$J11:$L260="Load3"))) + Allowance!S27, _xlpm.Bal - (PRODUCT(COUNTIFS(Allowance!$G11:$I260, "Gift", Allowance!$J11:$L260, "Clear3"), _xlpm.Bal)))} -> 0 | L5: {=_xlfn.LET(_xlpm.Bal, SUMPRODUCT(Allowance!$D11:$F260*((Allowance!$G11:$I260="Want")*(Allowance!$J11:$L260="Slot3"))) - SUMPRODUCT(Allowance!$D11:$F260*((Allowance!$G11:$I260="Want")*(Allowance!$J11:$L260="Load3"))) + Allowance!S30, _xlpm.Bal - (PRODUCT(COUNTIFS(Allowance!$G11:$I260, "Want", Allowance!$J11:$L260, "Clear3"), _xlpm.Bal)))} -> 0

Sheet Stipend
D2: {=SUMPRODUCT(Stipend!$D4:$F253*((Stipend!$G4:$I253="Load")*((Stipend!$G4:$I253<>"")+(Stipend!$G4:$I253=""))))} -> 0 | G2: {=SUMPRODUCT(Stipend!$D4:$F253*(((Stipend!$G4:$I253="Hold")*(Stipend!$J4:$L253<>"Return"))+((Stipend!$G4:$I253="Out")+(Stipend!$G4:$I253<>"Load"))))} -> 0 | J2: =D2-G2 -> 0
B3: DATE | D3: AMOUNT | G3: PURCHASE | J3: SPECIFIC

Sheet GCash
D2: {=SUMPRODUCT(GCash!$D4:$F253*((GCash!$G4:$I253="Load")*((GCash!$G4:$I253<>"")+(GCash!$G4:$I253=""))))} -> 0 | G2: {=SUMPRODUCT(GCash!$D4:$F253*(((GCash!$G4:$I253="Hold")*(GCash!$J4:$L253<>"Return"))+((GCash!$G4:$I253="Out")+(GCash!$G4:$I253<>"Load"))))} -> 0 | J2: =D2-G2 -> 0
B3: DATE | D3: AMOUNT | G3: PURCHASE | J3: SPECIFIC

Sheet Maya
D2: {=SUMPRODUCT(Maya!$D5:$F254*(((Maya!$G5:$G254="Wallet")*(Maya!$H5:$H254="Load"))+((Maya!$G5:$G254="Savings")*(Maya!$H5:$H254="Transfer"))))} -> 0 | G2: {=SUMPRODUCT(Maya!$D5:$F254*(Maya!$G5:$G254="Wallet")*(((Maya!$H5:$H254="Hold")*(Maya!$I5:$K254<>"Return"))+(Maya!$H5:$H254="Transfer")+(Maya!$H5:$H254="Out")))} -> 0 | I2: =D2-G2 -> 0
D3: {=SUMPRODUCT(Maya!$D5:$F254*(((Maya!$G5:$G254="Savings")*((Maya!$H5:$H254="Load")+(Maya!$H5:$H254="Interest")))+((Maya!$G5:$G254="Wallet")*(Maya!$H5:$H254="Transfer"))))} -> 0 | G3: {=SUMPRODUCT(Maya!$D5:$F254*(Maya!$G5:$G254="Savings")*(((Maya!$H5:$H254="Hold")*(Maya!$I5:$K254<>"Return"))+(Maya!$H5:$H254="Transfer")+(Maya!$H5:$H254="Out")))} -> 0 | I3: =D3-G3 -> 0
B4: DATE | D4: AMOUNT | G4: CATEGORY | H4: PURCHASE | I4: SPECIFIC

Sheet CIMB
D2: {=SUMPRODUCT(CIMB!$D5:$F254*(((CIMB!$G5:$G254="UpSave")*((CIMB!$H5:$H254="Load")+(CIMB!$H5:$H254="Interest")))+((CIMB!$G5:$G254="GSave")*(CIMB!$H5:$H254="Transfer"))))} -> 0 | G2: {=SUMPRODUCT(CIMB!$D5:$F254*(CIMB!$G5:$G254="UpSave")*(((CIMB!$H5:$H254="Hold")*(CIMB!$I5:$K254<>"Return"))+(CIMB!$H5:$H254="Transfer")+(CIMB!$H5:$H254="Out")))} -> 0 | I2: =D2-G2 -> 0
D3: {=SUMPRODUCT(CIMB!$D5:$F254*(((CIMB!$G5:$G254="GSave")*((CIMB!$H5:$H254="Load")+(CIMB!$H5:$H254="Interest")))+((CIMB!$G5:$G254="UpSave")*(CIMB!$H5:$H254="Transfer"))))} -> 0 | G3: {=SUMPRODUCT(CIMB!$D5:$F254*(CIMB!$G5:$G254="Gsave")*(((CIMB!$H5:$H254="Hold")*(CIMB!$I5:$K254<>"Return"))+(CIMB!$H5:$H254="Transfer")+(CIMB!$H5:$H254="Out")))} -> 0 | I3: =D3-G3 -> 0
B4: DATE | D4: AMOUNT | G4: CATEGORY | H4: PURCHASE | I4: SPECIFIC
